[
  {
    "_id": "6788a1d739d993425081787e",
    "articleId": "1736995590157",
    "userToken": "kajfhu",
    "content": "hello hello 你好啊外国朋友  我给你介绍几个比较实用的中国字：齉齾爩麤靇灪龖麤戀虋龘龘瓥齉齾爩鱻麤靇灪龖麤癵驫虛戀虋讟钃麷鞻韽韾顟顠饙饙鷌騱饐龗鱻爩麤灪癵籗麟戀虋讟钃鸜麷龘龘羉齉齾爩鱻麤靇灪龖赑瘸驫巖戀虋讟钃鸜麷鞻韽韾顟顠饙饙騆騱饐龗鱻爩麤灪癵籮麟戀虋讟钃鸜麥龘龘瓥齉齾爩鱻麤靇灪龖麤癵驫慮戀虋讟钃鸜麷鞻韽韾顟顠饙饙騆騱饐龗鱻爩麤灪癵籠麟戀虋讟钃鸜麷鞻鬱靊烝離齺魕爧蠿齺虪龘龘羉齉",
    "createdAt": "2025-01-16 "
  },
  {
    "_id": "6788a1e639d993425081787f",
    "articleId": "1736995590157",
    "userToken": "kajfhu",
    "content": "，可以参考下面几个绕口令： 喷：八百标兵奔北坡，北坡炮兵并排跑，炮兵怕把标兵碰，标兵怕碰炮兵炮。 弹：断头台倒吊短单刀，歹徒登台偷短刀，断头台塌盗倒，对对短刀叮当掉。 啃：哥跨瓜筐过宽沟，快过宽沟观怪狗，光顾观狗瓜扣，瓜滚空哥狗。 吐：无父母，不孤独，五叔督促苦读书，不读书，无出路，独宿竹屋哭不住",
    "createdAt": "2025-01-16 "
  },
  {
    "_id": "6788a1fd39d9934250817880",
    "articleId": "1736995590157",
    "userToken": "kajfhu",
    "content": "大家让一让，让我来撩她。 I love three things in this world. Sun, moon and you. Sun for morning, Moon for night, and you forever. 浮世三千，吾爱有三。 日，月与卿。 日为朝， 月为暮， 卿为朝朝暮暮",
    "createdAt": "2025-01-16 "
  },
  {
    "_id": "6788a69439d9934250817884",
    "articleId": "1736997263278",
    "userToken": "wdhaia111",
    "content": "不错不错",
    "createdAt": "2025-01-16 "
  },
  {
    "_id": "6788a98039d9934250817885",
    "articleId": "1736995949016",
    "userToken": "wdhaia111",
    "content": "不错不错",
    "createdAt": "2025-01-16 "
  },
  {
    "_id": "6788e76d39d993425081788d",
    "articleId": "1736995729428",
    "userToken": "saq1",
    "content": "666",
    "createdAt": "2025-01-16 "
  },
  {
    "_id": "6788e96f39d993425081788e",
    "articleId": "1736994076660",
    "userToken": "saq1",
    "content": "烦烦烦.",
    "createdAt": "2025-01-16 "
  },
  {
    "_id": "6789ca4e71cafbc45e8bba1c",
    "articleId": "1736997263278",
    "userToken": "hahaw231",
    "content": "1",
    "createdAt": "2025-01-17 "
  },
  {
    "_id": "6789cd8871cafbc45e8bba1e",
    "articleId": "1736993876325",
    "userToken": "hahaw231",
    "content": "。我是西班牙人，但是我会说一点儿中文因为我学习中文在大学。",
    "createdAt": "2025-01-17 "
  },
  {
    "_id": "6789cd9d71cafbc45e8bba1f",
    "articleId": "1736997535167",
    "userToken": "hahaw231",
    "content": "你还不贪呢，你天蓬下凡了你，我才是真的不贪",
    "createdAt": "2025-01-17 "
  },
  {
    "_id": "6789cdaa71cafbc45e8bba20",
    "articleId": "1736997358073",
    "userToken": "hahaw231",
    "content": "That looks amazing!",
    "createdAt": "2025-01-17 "
  },
  {
    "_id": "6789cdb371cafbc45e8bba21",
    "articleId": "1736997724300",
    "userToken": "hahaw231",
    "content": "不错不错",
    "createdAt": "2025-01-17 "
  },
  {
    "_id": "6789e94971cafbc45e8bba23",
    "articleId": "1737091354644",
    "userToken": "kajfhu",
    "content": "wdwad",
    "createdAt": "2025-01-17 "
  },
  {
    "_id": "6789ffca71cafbc45e8bba2f",
    "articleId": "1736993876325",
    "userToken": "11111111",
    "content": "1",
    "createdAt": "2025-01-17 "
  },
  {
    "_id": "678a043671cafbc45e8bba38",
    "articleId": "1737098177298",
    "userToken": "123456",
    "content": "123",
    "createdAt": "2025-01-17 "
  },
  {
    "_id": "67aee1ca855cfe6539d1aecc",
    "articleId": "1736995902844",
    "userToken": "saq1",
    "content": "阿松大",
    "createdAt": "2025-02-14 "
  },
  {
    "_id": "67b2028a6a6c0fd4af4b21db",
    "articleId": "1736993876325",
    "userToken": "123456789",
    "content": "wowowo",
    "createdAt": "2025-02-16 "
  },
  {
    "_id": "67b202ed6a6c0fd4af4b21df",
    "articleId": "1739719341888",
    "userToken": "123456789",
    "content": "dsfsd",
    "createdAt": "2025-02-16 "
  }
]